LICENSE
README.md
requirements.txt
setup.py
docs/Makefile
docs/api.rst
docs/components.rst
docs/conf.py
docs/contribution_guide.rst
docs/drivers.rst
docs/getting_started.rst
docs/index.rst
docs/introduction.rst
docs/make.bat
docs/_ext/runcible_autodoc.py
docs/_static/theme_overrides.css
docs/screenshots/network_topology_3switch.png
examples/cumulus_mclag/mdb.yaml
examples/cumulus_mclag/common/dir.yaml
examples/cumulus_mclag/common/dist.yaml
examples/cumulus_mclag/common/vlans.yaml
examples/cumulus_mclag/mclag_groups/dir.yaml
examples/cumulus_mclag/mclag_groups/spine1.yaml
examples/cumulus_mclag/switches/dir.yaml
examples/cumulus_mclag/switches/dist1.yaml
examples/cumulus_mclag/switches/dist2.yaml
examples/cumulus_mclag/switches/spine1a.yaml
examples/cumulus_mclag/switches/spine1b.yaml
examples/mergedb_getting_started/mdb.yaml
examples/mergedb_getting_started/layers/core.yaml
examples/mergedb_getting_started/layers/dir.yaml
examples/mergedb_getting_started/layers/dist.yaml
examples/mergedb_getting_started/layers/ssh_auth.yaml
examples/mergedb_getting_started/layers/vlans.yaml
examples/mergedb_getting_started/routers/dir.yaml
examples/mergedb_getting_started/routers/router1.yaml
examples/mergedb_getting_started/switches/core.yaml
examples/mergedb_getting_started/switches/dir.yaml
examples/mergedb_getting_started/switches/dist1.yaml
examples/mergedb_getting_started/switches/dist2.yaml
examples/yaml/cumulus_switch.yaml
runcible/__init__.py
runcible/__main__.py
runcible/api.py
runcible.egg-info/PKG-INFO
runcible.egg-info/SOURCES.txt
runcible.egg-info/dependency_links.txt
runcible.egg-info/entry_points.txt
runcible.egg-info/requires.txt
runcible.egg-info/top_level.txt
runcible/core/__init__.py
runcible/core/callback.py
runcible/core/callbacks.py
runcible/core/cli.py
runcible/core/common.py
runcible/core/device.py
runcible/core/errors.py
runcible/core/fabricparser.py
runcible/core/need.py
runcible/core/plugin_registry.py
runcible/core/terminalcallbacks.py
runcible/core/utilities.py
runcible/drivers/__init__.py
runcible/drivers/cumulus.py
runcible/drivers/driver.py
runcible/modules/__init__.py
runcible/modules/bond.py
runcible/modules/bonds.py
