Metadata-Version: 2.1
Name: runcible
Version: 0.2.0
Summary: UNKNOWN
Home-page: https://github.com/graysonhead/runcible
Author: Grayson Head
Author-email: grayson@graysonhead.net
License: GPL V3
Project-URL: Repository, https://github.com/graysonhead/runcible
Project-URL: Documentation, https://runcible.readthedocs.io/en/latest/index.html
Project-URL: Gitter, https://gitter.im/runcible_project/community
Platform: UNKNOWN
Classifier: Development Status :: 3 - Alpha
Classifier: Intended Audience :: Telecommunications Industry
Classifier: License :: OSI Approved :: GNU General Public License v3 (GPLv3)
Classifier: Programming Language :: Python :: 3.5
Classifier: Programming Language :: Python :: 3.6
Classifier: Programming Language :: Python :: 3.7
Requires-Python: >=3.5, <4
